setup.py
bin/fxml.py
fastxml/__init__.py
fastxml/fastxml.py
fastxml/inferencer.pyx
fastxml/metrics.py
fastxml/proc.py
fastxml/splitter.c
fastxml/splitter.pyx
fastxml/trainer.py
fastxml/weights.py
fastxml.egg-info/PKG-INFO
fastxml.egg-info/SOURCES.txt
fastxml.egg-info/dependency_links.txt
fastxml.egg-info/requires.txt
fastxml.egg-info/top_level.txt