Metadata-Version: 1.1
Name: fastxml
Version: 2.0.0
Summary: FastXML Extreme Multi-label Classification Algorithm
Home-page: https://github.com/refefer/fastxml
Author: Andrew Stanton
Author-email: refefer@gmail.com
License: LICENSE
Platform: UNKNOWN
Classifier: License :: OSI Approved :: Apache Software License
Classifier: Programming Language :: Python :: 2.7
Classifier: Operating System :: OS Independent
